sshbind-0.0.2.dist-info/METADATA
sshbind-0.0.2.dist-info/WHEEL
sshbind-0.0.2.dist-info/licenses/LICENSE
sshbind/__init__.py
sshbind/_lib_sshbind_wrapper.cpython-310-powerpc64le-linux-gnu.so
sshbind-0.0.2.dist-info/RECORD
