Metadata-Version: 2.4
Name: sshbind
Version: 0.0.2
Classifier: Programming Language :: Rust
Classifier: Programming Language :: Python :: Implementation :: CPython
Classifier: Programming Language :: Python :: Implementation :: PyPy
License-File: LICENSE
Home-Page: https://github.com/Xyhlon/SSHBindpy
Author: Maximilian Philipp <maxkon2000@gmail.com>
Author-email: Maximilian Philipp <maxkon2000@gmail.com>
License: MIT
Requires-Python: >=3.8
Project-URL: Source Code, https://github.com/Xyhlon/SSHBindpy
